granite/SVqcVCF.py
granite/__init__.py
granite/_version.py
granite/blackList.py
granite/cleanVCF.py
granite/comHet.py
granite/filterByTag.py
granite/geneList.py
granite/granite.py
granite/lib/__init__.py
granite/lib/fasta_parser.py
granite/lib/mpileup_parser.py
granite/lib/pedigree_parser.py
granite/lib/shared_functions.py
granite/lib/shared_vars.py
granite/lib/vcf_parser.py
granite/mpileupCounts.py
granite/novoCaller.py
granite/qcVCF.py
granite/rckTar.py
granite/toBig.py
granite/toPED.py
granite/validateVCF.py
granite/whiteList.py
granite_suite-0.5.0.dist-info/METADATA
granite_suite-0.5.0.dist-info/WHEEL
granite_suite-0.5.0.dist-info/entry_points.txt
granite_suite-0.5.0.dist-info/licenses/LICENSE.txt
granite_suite-0.5.0.dist-info/RECORD
