Metadata-Version: 2.4
Name: granite-suite
Version: 0.5.0
Summary: granite is a collection of software to call, filter and work with genomic variants.
License: MIT
License-File: LICENSE.txt
Author: Michele Berselli
Author-email: berselli.michele@gmail.com
Requires-Python: >=3.9,<4.0
Classifier: License :: OSI Approved :: MIT License
Classifier: Operating System :: POSIX :: Linux
Classifier: Programming Language :: Python
Classifier: Programming Language :: Python :: 3
Classifier: Programming Language :: Python :: 3.9
Classifier: Programming Language :: Python :: 3.10
Classifier: Programming Language :: Python :: 3.11
Classifier: Programming Language :: Python :: 3.12
Classifier: Programming Language :: Python :: 3.13
Classifier: Programming Language :: Python :: 3.14
Requires-Dist: bitarray (>=2.9.2,<3.0.0)
Requires-Dist: h5py (>=3.11.0,<4.0.0)
Requires-Dist: matplotlib (>=3.9.0,<4.0.0)
Requires-Dist: numpy (>=1.26.4,<2.0.0)
Requires-Dist: pysam (>=0.22.1,<0.23.0)
Requires-Dist: pytabix (>=0.1,<0.2)
Project-URL: Homepage, https://github.com/dbmi-bgm/granite
Project-URL: Repository, https://github.com/dbmi-bgm/granite
